torchsqlite-0.1.1.dist-info/METADATA
torchsqlite-0.1.1.dist-info/WHEEL
torchsqlite-0.1.1.dist-info/entry_points.txt
torchsqlite-0.1.1.dist-info/licenses/LICENSE
torchsqlite/__init__.py
torchsqlite/dataset.py
torchsqlite-0.1.1.dist-info/RECORD
