Metadata-Version: 2.1
Name: torchsqlite
Version: 0.1.1
Summary: Sqlite based dataset for torch.
Author-Email: Taeyong Jeon <taeyongjeon24@gmail.com>
License: MIT
Requires-Python: >=3.10
Requires-Dist: torch>=2.6.0
Requires-Dist: pandas>=2.2.3
